control_ai/__init__.py
control_ai-0.0.0.dist-info/LICENSE
control_ai-0.0.0.dist-info/METADATA
control_ai-0.0.0.dist-info/WHEEL
control_ai-0.0.0.dist-info/top_level.txt
control_ai-0.0.0.dist-info/RECORD
